passenger_asgi/__init__.py
passenger_asgi/adapter.py
passenger_asgi/api.py
passenger_asgi/entrypoint.py
passenger_asgi/passenger.py
passenger_asgi/preloader.py
passenger_asgi/session.py
passenger_asgi/asyncio/__init__.py
passenger_asgi/asyncio/asgi_statemachine.py
passenger_asgi/asyncio/asgi_typing.py
passenger_asgi/asyncio/exceptions.py
passenger_asgi/asyncio/lifespan.py
passenger_asgi/asyncio/main.py
passenger_asgi/asyncio/protocol_filter.py
passenger_asgi/asyncio/websocket.py
passenger_asgi/asyncio/wsgi.py
passenger_asgi/wsgi/__init__.py
passenger_asgi/wsgi/main.py
passenger_asgi/wsgi/restricted_input.py
passenger_asgi-0.1.0.dist-info/METADATA
passenger_asgi-0.1.0.dist-info/WHEEL
passenger_asgi-0.1.0.dist-info/entry_points.txt
passenger_asgi-0.1.0.dist-info/top_level.txt
passenger_asgi-0.1.0.dist-info/RECORD
